logging_utils_tddschn/__init__.py
logging_utils_tddschn/utils.py
logging_utils_tddschn-0.1.10.dist-info/LICENSE
logging_utils_tddschn-0.1.10.dist-info/WHEEL
logging_utils_tddschn-0.1.10.dist-info/METADATA
logging_utils_tddschn-0.1.10.dist-info/RECORD
