Metadata-Version: 2.1
Name: logging-utils-tddschn
Version: 0.1.10
Summary: Logging utilities for personal use.
Home-page: https://github.com/tddschn/logging-utils-tddschn
License: MIT
Keywords: logging
Author: Xinyuan Chen
Author-email: 45612704+tddschn@users.noreply.github.com
Requires-Python: >=3.10,<4.0
Classifier: Intended Audience :: Developers
Classifier: License :: OSI Approved :: MIT License
Classifier: Programming Language :: Python :: 3
Classifier: Programming Language :: Python :: 3.10
Classifier: Topic :: System :: Logging
Classifier: Topic :: Utilities
Requires-Dist: utils-tddschn (>=1.0.1,<2.0.0)
Project-URL: Repository, https://github.com/tddschn/logging-utils-tddschn
